{
  "schema": "ui.v1",
  "includeToolDataSnapshot": true,
  "allowedToolRefs": [
    "shop.listProducts",
    "shop.searchProducts",
    "shop.getProduct",
    "shop.listCategories",
    "shop.listProductsByCategory",
    "shop.listProductsSorted",
    "shop.getCart",
    "shop.addToCart",
    "finance.getSummary",
    "finance.getAccounts",
    "finance.getTransactions",
    "finance.searchTransactions",
    "finance.getExpenses",
    "finance.getBudgets",
    "finance.getExpenseAnalytics",
    "finance.getTransactionAnalytics"
  ],
  "includeBindings": true,
  "includeSubscriptions": true,
  "computeRules": []
}